file_tools_zxw/__init__.py
file_tools_zxw/zip文件读取.py
file_tools_zxw/后端服务_Excel数据_流传输.py
file_tools_zxw/文件_文件夹_扫描.py
file_tools_zxw/文件_空间占用.py
file_tools_zxw/文件夹_创建.py
file_tools_zxw/磁盘_剩余空间.py
file_tools_zxw/移动硬盘_识别.py
file_tools_zxw/项目_根目录.py
file_tools_zxw-1.2.3.dist-info/METADATA
file_tools_zxw-1.2.3.dist-info/WHEEL
file_tools_zxw-1.2.3.dist-info/top_level.txt
file_tools_zxw-1.2.3.dist-info/RECORD
