Metadata-Version: 2.1
Name: file-tools-zxw
Version: 1.2.3
Summary: 常用的文件操作的中文工具包,如文件查找,创建文件夹, 文件夹查找,ZIP文件读取等.
Home-page: https://github.com/yourusername/mypackage
Author: XueWei Zhang
Author-email: tonson_predict@qq.com
License: UNKNOWN
Platform: UNKNOWN
Classifier: Programming Language :: Python :: 3.8
Classifier: License :: OSI Approved :: MIT License
Classifier: Operating System :: OS Independent
Requires-Dist: xlwt
Requires-Dist: fastapi
Requires-Dist: psutil
